pyamazonlandsat/__init__.py
pyamazonlandsat/downloader.py
pyamazonlandsat/product.py
pyamazonlandsat/service.py
pyamazonlandsat/utils.py
pyamazonlandsat/version.py
pys3landsat-0.2.4.data/scripts/pys3landsat
pys3landsat-0.2.4.dist-info/LICENSE
pys3landsat-0.2.4.dist-info/METADATA
pys3landsat-0.2.4.dist-info/WHEEL
pys3landsat-0.2.4.dist-info/top_level.txt
pys3landsat-0.2.4.dist-info/RECORD
